__init__.py
pyrealsense_multi/__init__.py
pyrealsense_multi/align_frames.py
pyrealsense_multi/record_sync.py
pyrealsense_multi-0.0.1.dist-info/LICENSE.txt
pyrealsense_multi-0.0.1.dist-info/METADATA
pyrealsense_multi-0.0.1.dist-info/WHEEL
pyrealsense_multi-0.0.1.dist-info/top_level.txt
pyrealsense_multi-0.0.1.dist-info/RECORD
