Metadata-Version: 2.1
Name: pyrealsense_multi
Version: 0.0.1
Summary: A small package for multiple Intel RealSense cameras
Author-email: Puzzle Puzhe Li <609788969@qq.com>
Project-URL: Homepage, https://github.com/BMI-Free/multi_camera_recording
Classifier: Programming Language :: Python :: 3
Classifier: License :: OSI Approved :: MIT License
Classifier: Operating System :: OS Independent
Requires-Python: >=3.9
License-File: LICENSE.txt
